rafe/__init__.py
rafe/__main__.py
rafe/build.py
rafe/cfgraph.py
rafe/cli.py
rafe/cli_api.py
rafe/config.py
rafe/griffe_util.py
rafe/logger.py
rafe/main.py
rafe/metadata.py
rafe/plugin.py
rafe/source.py
rafe/utils.py
rafe-0.1.6.dist-info/LICENSE.txt
rafe-0.1.6.dist-info/METADATA
rafe-0.1.6.dist-info/WHEEL
rafe-0.1.6.dist-info/entry_points.txt
rafe-0.1.6.dist-info/top_level.txt
rafe-0.1.6.dist-info/RECORD
