Metadata-Version: 2.1
Name: rafe
Version: 0.1.6
Summary: A build and environment analysis tool for Python
Home-page: https://github.com/Quansight/rafe
Author: Anirrudh Krishnan, Dillon Roach, Ilan Schnell
License: BSD
Platform: UNKNOWN
Requires-Dist: typer (>=0.7.0)
Requires-Dist: griffe (==0.30.1)
Requires-Dist: rich
Requires-Dist: GitPython
Requires-Dist: aiohttp
Requires-Dist: aiofiles
Requires-Dist: pyyaml
Requires-Dist: requests
Requires-Dist: pydantic
